{
	"archive" : {},
	"artifacts" : 
	[
		{
			"path" : "conversion/libCONVERSIONLIB.a"
		}
	],
	"backtrace" : 1,
	"backtraceGraph" : 
	{
		"commands" : 
		[
			"add_library",
			"add_definitions",
			"include_directories",
			"target_include_directories"
		],
		"files" : 
		[
			"conversion/CMakeLists.txt",
			"CMakeLists.txt"
		],
		"nodes" : 
		[
			{
				"file" : 0
			},
			{
				"command" : 0,
				"file" : 0,
				"line" : 4,
				"parent" : 0
			},
			{
				"file" : 1
			},
			{
				"command" : 1,
				"file" : 1,
				"line" : 13,
				"parent" : 2
			},
			{
				"command" : 2,
				"file" : 1,
				"line" : 16,
				"parent" : 2
			},
			{
				"command" : 3,
				"file" : 0,
				"line" : 8,
				"parent" : 0
			}
		]
	},
	"compileGroups" : 
	[
		{
			"compileCommandFragments" : 
			[
				{
					"fragment" : "-g -isysroot /Library/Developer/CommandLineTools/SDKs/MacOSX11.3.sdk"
				},
				{
					"fragment" : "-std=gnu++11"
				}
			],
			"defines" : 
			[
				{
					"backtrace" : 3,
					"define" : "DSA_PQ_LIST"
				},
				{
					"backtrace" : 3,
					"define" : "DSA_STACK_LIST"
				}
			],
			"includes" : 
			[
				{
					"backtrace" : 4,
					"path" : "/Users/melody/Downloads/test/Junhui-Deng-DSAPP-CMAKE/src"
				},
				{
					"backtrace" : 5,
					"path" : "/Users/melody/Downloads/test/Junhui-Deng-DSAPP-CMAKE/src/conversion"
				}
			],
			"language" : "CXX",
			"languageStandard" : 
			{
				"backtraces" : 
				[
					1
				],
				"standard" : "11"
			},
			"sourceIndexes" : 
			[
				0
			]
		}
	],
	"id" : "CONVERSIONLIB::@dae4621177dd7c573cc2",
	"name" : "CONVERSIONLIB",
	"nameOnDisk" : "libCONVERSIONLIB.a",
	"paths" : 
	{
		"build" : "conversion",
		"source" : "conversion"
	},
	"sourceGroups" : 
	[
		{
			"name" : "Source Files",
			"sourceIndexes" : 
			[
				0
			]
		}
	],
	"sources" : 
	[
		{
			"backtrace" : 1,
			"compileGroupIndex" : 0,
			"path" : "conversion/convert.cpp",
			"sourceGroupIndex" : 0
		}
	],
	"type" : "STATIC_LIBRARY"
}
